raspigaragealert/__init__.py
raspigaragealert/alert.py
raspigaragealert/garage_door.py
raspigaragealert/services/__init__.py
raspigaragealert/services/matrix.py
raspigaragealert/services/mqtt.py
raspigaragealert/tests/__init__.py
raspigaragealert-0.6.0.dist-info/LICENSE
raspigaragealert-0.6.0.dist-info/METADATA
raspigaragealert-0.6.0.dist-info/WHEEL
raspigaragealert-0.6.0.dist-info/top_level.txt
raspigaragealert-0.6.0.dist-info/RECORD
