Metadata-Version: 2.1
Name: raspigaragealert
Version: 0.6.0
Summary: Generate an alert when your garage door is left open
Home-page: https://github.com/djotaku/raspi_garage_alert
Author: Eric Mesa
Author-email: eric@ericmesa.com
License: UNKNOWN
Keywords: Raspberry Pi
Platform: UNKNOWN
Requires-Dist: RPi.GPIO (==0.7.0)
Requires-Dist: paho.mqtt (==1.5)
Requires-Dist: xdgenvpy
Requires-Dist: matrix-nio
